{"assets":{"23A5CCB9230FB17299FEEC5D7C6B96C1":{"type":"texture","index":121,"assetRequest":{"type":"slide","state":"outgoing","slide":"D4EBA150-C05A-4054-B3A8-AB94F17A692E"},"url":"assets/23A5CCB9230FB17299FEEC5D7C6B96C1.svg","width":720,"height":540},"C9E58CC1B4809378F01721D2F5C59BC3":{"type":"texture","index":122,"assetRequest":{"type":"slide","state":"incoming","slide":"CD22BAB6-5465-485B-9AF9-C003EBE9A6D5"},"url":"assets/C9E58CC1B4809378F01721D2F5C59BC3.svg","width":720,"height":540}},"events":[{"effects":[{"beginTime":0,"baseLayer":{"animations":[],"initialState":{"affineTransform":[1,0,0,1,0,0],"masksToBounds":true,"rotation":0,"scale":1,"position":{"pointX":360,"pointY":270},"width":720,"sublayerTransform":[1,0,0,0,0,1,0,0,0,0,1,0,0,0,0,1],"contentsRect":{"y":0,"x":0,"width":1,"height":1},"opacity":1,"edgeAntialiasingMask":0,"height":540,"hidden":false,"anchorPoint":{"pointX":0.5,"pointY":0.5}},"objectID":"0","layers":[{"animations":[],"initialState":{"affineTransform":[1,0,0,1,0,0],"masksToBounds":false,"rotation":0,"scale":1,"position":{"pointX":360,"pointY":270},"width":720,"sublayerTransform":[1,0,0,0,0,1,0,0,0,0,1,-0.0007001582493355197,0,0,0,1],"contentsRect":{"y":0,"x":0,"width":1,"height":1},"opacity":1,"edgeAntialiasingMask":15,"height":540,"hidden":false,"anchorPoint":{"pointX":0.5,"pointY":0.5}},"layers":[{"animations":[],"layers":[],"initialState":{"affineTransform":[1,0,0,1,0,0],"masksToBounds":false,"rotation":0,"scale":1,"position":{"pointX":360,"pointY":270},"width":720,"sublayerTransform":[1,0,0,0,0,1,0,0,0,0,1,0,0,0,0,1],"contentsRect":{"y":0,"x":0,"width":1,"height":1},"opacity":1,"edgeAntialiasingMask":0,"height":540,"hidden":false,"anchorPoint":{"pointX":0.5,"pointY":0.5}},"texture":"C9E58CC1B4809378F01721D2F5C59BC3"},{"animations":[{"from":{"scalar":false},"beginTime":0,"repeatCount":0,"fillMode":"both","property":"hidden","duration":0.01,"to":{"scalar":true}}],"layers":[],"initialState":{"affineTransform":[1,0,0,1,0,0],"masksToBounds":false,"rotation":0,"scale":1,"position":{"pointX":360,"pointY":270},"width":720,"sublayerTransform":[1,0,0,0,0,1,0,0,0,0,1,0,0,0,0,1],"contentsRect":{"y":0,"x":0,"width":1,"height":1},"opacity":1,"edgeAntialiasingMask":0,"height":540,"hidden":false,"anchorPoint":{"pointX":0.5,"pointY":0.5}},"texture":"23A5CCB9230FB17299FEEC5D7C6B96C1"}]}]},"effects":[],"duration":0.01,"type":"transition","name":"none","objectID":"0"}],"automaticPlay":false,"hyperlinks":[],"accessibility":[{"text":"Dorsal - high emissivity","targetRectangle":{"y":448,"x":79.19999980926514,"width":246.7265625,"height":27.21484375}},{"text":"(matte surface)","targetRectangle":{"y":476,"x":79.19999980926514,"width":161.37890625,"height":27.21484375}},{"text":"Ventral - low emissivity","targetRectangle":{"y":454,"x":397.1999998092651,"width":242.73046875,"height":27.21484375}},{"text":"(shiny surface)","targetRectangle":{"y":482,"x":397.1999998092651,"width":157.3828125,"height":27.21484375}},{"text":"Infrared radiation","targetRectangle":{"y":69,"x":193.6787109375,"width":332.642578125,"height":48.560546875}},{"text":"image.pdf","targetRectangle":{"y":288,"x":360,"width":318,"height":118.25}},{"text":"image.pdf","targetRectangle":{"y":258,"x":84,"width":258,"height":172.625}},{"text":"Mojave fringe-toed lizard Uma scoparia","targetRectangle":{"y":166,"x":157.1999998092651,"width":417.515625,"height":27.21484375}}],"baseLayer":{"animations":[],"initialState":{"affineTransform":[1,0,0,1,0,0],"masksToBounds":true,"rotation":0,"scale":1,"position":{"pointX":360,"pointY":270},"width":720,"sublayerTransform":[1,0,0,0,0,1,0,0,0,0,1,0,0,0,0,1],"contentsRect":{"y":0,"x":0,"width":1,"height":1},"opacity":1,"edgeAntialiasingMask":0,"height":540,"hidden":false,"anchorPoint":{"pointX":0.5,"pointY":0.5}},"objectID":"0","layers":[{"animations":[],"initialState":{"affineTransform":[1,0,0,1,0,0],"masksToBounds":false,"rotation":0,"scale":1,"position":{"pointX":360,"pointY":270},"width":720,"sublayerTransform":[1,0,0,0,0,1,0,0,0,0,1,-0.0007001582493355197,0,0,0,1],"contentsRect":{"y":0,"x":0,"width":1,"height":1},"opacity":1,"edgeAntialiasingMask":15,"height":540,"hidden":false,"anchorPoint":{"pointX":0.5,"pointY":0.5}},"layers":[{"animations":[],"layers":[],"initialState":{"affineTransform":[1,0,0,1,0,0],"masksToBounds":false,"rotation":0,"scale":1,"position":{"pointX":360,"pointY":270},"width":720,"sublayerTransform":[1,0,0,0,0,1,0,0,0,0,1,0,0,0,0,1],"contentsRect":{"y":0,"x":0,"width":1,"height":1},"opacity":1,"edgeAntialiasingMask":0,"height":540,"hidden":false,"anchorPoint":{"pointX":0.5,"pointY":0.5}},"texture":"23A5CCB9230FB17299FEEC5D7C6B96C1"}]}]}}]}