{"assets":{"8625CA83FBE023D544BBFB34E4BD76C5":{"type":"texture","index":72,"assetRequest":{"type":"slide","state":"incoming","slide":"84BDDCD0-A9F2-4AE9-A4A4-D15604B85871"},"url":"assets/8625CA83FBE023D544BBFB34E4BD76C5.svg","width":1024,"height":768},"8DD44E9BD347E397376A0EFD01936ED1":{"type":"texture","index":71,"assetRequest":{"type":"slide","state":"outgoing","slide":"1BAEE060-1784-4A17-ADD5-1CB93F0C678F"},"url":"assets/8DD44E9BD347E397376A0EFD01936ED1.svg","width":1024,"height":768}},"events":[{"effects":[{"beginTime":0,"baseLayer":{"animations":[],"initialState":{"affineTransform":[1,0,0,1,0,0],"masksToBounds":true,"rotation":0,"scale":1,"position":{"pointX":512,"pointY":384},"width":1024,"sublayerTransform":[1,0,0,0,0,1,0,0,0,0,1,0,0,0,0,1],"contentsRect":{"y":0,"x":0,"width":1,"height":1},"opacity":1,"edgeAntialiasingMask":0,"height":768,"hidden":false,"anchorPoint":{"pointX":0.5,"pointY":0.5}},"objectID":"0","layers":[{"animations":[],"initialState":{"affineTransform":[1,0,0,1,0,0],"masksToBounds":false,"rotation":0,"scale":1,"position":{"pointX":512,"pointY":384},"width":1024,"sublayerTransform":[1,0,0,0,0,1,0,0,0,0,1,-0.0004922987690640373,0,0,0,1],"contentsRect":{"y":0,"x":0,"width":1,"height":1},"opacity":1,"edgeAntialiasingMask":15,"height":768,"hidden":false,"anchorPoint":{"pointX":0.5,"pointY":0.5}},"layers":[{"animations":[],"layers":[],"initialState":{"affineTransform":[1,0,0,1,0,0],"masksToBounds":false,"rotation":0,"scale":1,"position":{"pointX":512,"pointY":384},"width":1024,"sublayerTransform":[1,0,0,0,0,1,0,0,0,0,1,0,0,0,0,1],"contentsRect":{"y":0,"x":0,"width":1,"height":1},"opacity":1,"edgeAntialiasingMask":0,"height":768,"hidden":false,"anchorPoint":{"pointX":0.5,"pointY":0.5}},"texture":"8625CA83FBE023D544BBFB34E4BD76C5"},{"animations":[{"from":{"scalar":false},"beginTime":0,"repeatCount":0,"fillMode":"both","property":"hidden","duration":0.01,"to":{"scalar":true}}],"layers":[],"initialState":{"affineTransform":[1,0,0,1,0,0],"masksToBounds":false,"rotation":0,"scale":1,"position":{"pointX":512,"pointY":384},"width":1024,"sublayerTransform":[1,0,0,0,0,1,0,0,0,0,1,0,0,0,0,1],"contentsRect":{"y":0,"x":0,"width":1,"height":1},"opacity":1,"edgeAntialiasingMask":0,"height":768,"hidden":false,"anchorPoint":{"pointX":0.5,"pointY":0.5}},"texture":"8DD44E9BD347E397376A0EFD01936ED1"}]}]},"effects":[],"duration":0.01,"type":"transition","name":"none","objectID":"0"}],"automaticPlay":false,"hyperlinks":[],"accessibility":[{"text":"Main types:","targetRectangle":{"y":226,"x":111.2000005245209,"width":224.984375,"height":48.560546875}},{"text":"XY (male heterogametic)","targetRectangle":{"y":276,"x":142.700001001358,"width":419.595703125,"height":50.85905838012695}},{"text":"ZW (female heterogametic)","targetRectangle":{"y":328.102222442627,"x":142.700001001358,"width":460.3603515625,"height":50.85905838012695}},{"text":"Environmental sex determination","targetRectangle":{"y":380.2044448852539,"x":142.700001001358,"width":553.3935546875,"height":50.85905838012695}},{"text":"Sex Determination","targetRectangle":{"y":98,"x":256.99169921875,"width":510.0166015625,"height":68.9716796875}}],"baseLayer":{"animations":[],"initialState":{"affineTransform":[1,0,0,1,0,0],"masksToBounds":true,"rotation":0,"scale":1,"position":{"pointX":512,"pointY":384},"width":1024,"sublayerTransform":[1,0,0,0,0,1,0,0,0,0,1,0,0,0,0,1],"contentsRect":{"y":0,"x":0,"width":1,"height":1},"opacity":1,"edgeAntialiasingMask":0,"height":768,"hidden":false,"anchorPoint":{"pointX":0.5,"pointY":0.5}},"objectID":"0","layers":[{"animations":[],"initialState":{"affineTransform":[1,0,0,1,0,0],"masksToBounds":false,"rotation":0,"scale":1,"position":{"pointX":512,"pointY":384},"width":1024,"sublayerTransform":[1,0,0,0,0,1,0,0,0,0,1,-0.0004922987690640373,0,0,0,1],"contentsRect":{"y":0,"x":0,"width":1,"height":1},"opacity":1,"edgeAntialiasingMask":15,"height":768,"hidden":false,"anchorPoint":{"pointX":0.5,"pointY":0.5}},"layers":[{"animations":[],"layers":[],"initialState":{"affineTransform":[1,0,0,1,0,0],"masksToBounds":false,"rotation":0,"scale":1,"position":{"pointX":512,"pointY":384},"width":1024,"sublayerTransform":[1,0,0,0,0,1,0,0,0,0,1,0,0,0,0,1],"contentsRect":{"y":0,"x":0,"width":1,"height":1},"opacity":1,"edgeAntialiasingMask":0,"height":768,"hidden":false,"anchorPoint":{"pointX":0.5,"pointY":0.5}},"texture":"8DD44E9BD347E397376A0EFD01936ED1"}]}]}}]}